[
 {
  "docstatus": 0,
  "doctype": "Translation",
  "language": "en",
  "modified": "2019-02-12 22:28:25.939200",
  "name": "1351933bf0",
  "source_name": "Issue",
  "target_name": "Maintenance Job Card"
 },
 {
  "docstatus": 0,
  "doctype": "Translation",
  "language": "en",
  "modified": "2019-02-12 22:28:25.945471",
  "name": "035dbbde65",
  "source_name": "Issue",
  "target_name": "Maintenance Job Card"
 },
 {
  "docstatus": 0,
  "doctype": "Translation",
  "language": "en",
  "modified": "2019-02-12 22:28:25.951089",
  "name": "20b38e11df",
  "source_name": "Issue",
  "target_name": "Maintenance Job Card"
 },
 {
  "docstatus": 0,
  "doctype": "Translation",
  "language": "en",
  "modified": "2019-02-12 22:28:25.956898",
  "name": "13b21e1ca7",
  "source_name": "Issue",
  "target_name": "Maintenance Job Card"
 },
 {
  "docstatus": 0,
  "doctype": "Translation",
  "language": "en",
  "modified": "2019-02-12 22:28:25.962636",
  "name": "c0469d2445",
  "source_name": "Issue",
  "target_name": "Maintenance Job Card"
 },
 {
  "docstatus": 0,
  "doctype": "Translation",
  "language": "en",
  "modified": "2019-02-12 22:28:25.968331",
  "name": "0a73bec0df",
  "source_name": "Issue",
  "target_name": "Maintenance Job Card"
 },
 {
  "docstatus": 0,
  "doctype": "Translation",
  "language": "en",
  "modified": "2019-02-12 22:28:25.974001",
  "name": "6444b76636",
  "source_name": "Issue",
  "target_name": "Maintenance Job Card"
 },
 {
  "docstatus": 0,
  "doctype": "Translation",
  "language": "en",
  "modified": "2019-02-12 22:28:25.980870",
  "name": "cff30268e2",
  "source_name": "Issue",
  "target_name": "Maintenance Job Card"
 },
 {
  "docstatus": 0,
  "doctype": "Translation",
  "language": "en",
  "modified": "2019-02-12 22:28:25.986564",
  "name": "f3c047206e",
  "source_name": "Issue",
  "target_name": "Maintenance Job Card"
 },
 {
  "docstatus": 0,
  "doctype": "Translation",
  "language": "en",
  "modified": "2019-02-12 22:28:25.992398",
  "name": "5f97601219",
  "source_name": "Issue",
  "target_name": "Maintenance Job Card"
 },
 {
  "docstatus": 0,
  "doctype": "Translation",
  "language": "en",
  "modified": "2019-02-12 22:28:25.998193",
  "name": "2eb0210eb1",
  "source_name": "Issue",
  "target_name": "Maintenance Job Card"
 },
 {
  "docstatus": 0,
  "doctype": "Translation",
  "language": "en",
  "modified": "2019-02-12 22:28:26.004159",
  "name": "3e13daa441",
  "source_name": "Issue",
  "target_name": "Maintenance Job Card"
 },
 {
  "docstatus": 0,
  "doctype": "Translation",
  "language": "en",
  "modified": "2019-02-12 22:28:26.010320",
  "name": "b7c44f7735",
  "source_name": "Issue",
  "target_name": "Maintenance Job Card"
 },
 {
  "docstatus": 0,
  "doctype": "Translation",
  "language": "en",
  "modified": "2019-02-12 22:28:26.016322",
  "name": "98988f8fb3",
  "source_name": "Issue",
  "target_name": "Maintenance Job Card"
 },
 {
  "docstatus": 0,
  "doctype": "Translation",
  "language": "en",
  "modified": "2019-02-12 22:28:26.022037",
  "name": "be7b3b8bf9",
  "source_name": "Issue",
  "target_name": "Maintenance Job Card"
 },
 {
  "docstatus": 0,
  "doctype": "Translation",
  "language": "en",
  "modified": "2019-02-12 22:28:26.027861",
  "name": "995b1ad630",
  "source_name": "Issue",
  "target_name": "Maintenance Job Card"
 },
 {
  "docstatus": 0,
  "doctype": "Translation",
  "language": "en",
  "modified": "2019-02-12 22:28:26.034794",
  "name": "93df2e3bb8",
  "source_name": "Issue",
  "target_name": "Maintenance Job Card"
 },
 {
  "docstatus": 0,
  "doctype": "Translation",
  "language": "en",
  "modified": "2019-02-12 22:28:26.040543",
  "name": "823830c184",
  "source_name": "Issue",
  "target_name": "Maintenance Job Card"
 },
 {
  "docstatus": 0,
  "doctype": "Translation",
  "language": "en",
  "modified": "2019-02-12 22:28:26.046148",
  "name": "ad829a7b66",
  "source_name": "Issue",
  "target_name": "Maintenance Job Card"
 },
 {
  "docstatus": 0,
  "doctype": "Translation",
  "language": "en",
  "modified": "2019-02-12 22:28:26.051837",
  "name": "8aa9e72322",
  "source_name": "Issue",
  "target_name": "Maintenance Job Card"
 },
 {
  "docstatus": 0,
  "doctype": "Translation",
  "language": "en",
  "modified": "2019-02-12 22:28:26.057540",
  "name": "f3b279042a",
  "source_name": "Issue",
  "target_name": "Maintenance Job Card"
 },
 {
  "docstatus": 0,
  "doctype": "Translation",
  "language": "en",
  "modified": "2019-02-12 22:28:26.063368",
  "name": "2f4da53e93",
  "source_name": "Issue",
  "target_name": "Maintenance Job Card"
 },
 {
  "docstatus": 0,
  "doctype": "Translation",
  "language": "en",
  "modified": "2019-02-12 22:28:26.069562",
  "name": "61f344b4cc",
  "source_name": "Issue",
  "target_name": "Maintenance Job Card"
 },
 {
  "docstatus": 0,
  "doctype": "Translation",
  "language": "en",
  "modified": "2019-02-12 22:28:26.075133",
  "name": "9c8a23cb82",
  "source_name": "Issue",
  "target_name": "Maintenance Job Card"
 },
 {
  "docstatus": 0,
  "doctype": "Translation",
  "language": "en",
  "modified": "2019-02-12 22:28:26.080732",
  "name": "f72580021f",
  "source_name": "Issue",
  "target_name": "Maintenance Job Card"
 },
 {
  "docstatus": 0,
  "doctype": "Translation",
  "language": "en",
  "modified": "2019-02-12 22:28:26.086457",
  "name": "8c0f239309",
  "source_name": "Issue",
  "target_name": "Maintenance Job Card"
 },
 {
  "docstatus": 0,
  "doctype": "Translation",
  "language": "en",
  "modified": "2019-02-12 22:28:26.092257",
  "name": "6e0d92fbd9",
  "source_name": "Issue",
  "target_name": "Maintenance Job Card"
 },
 {
  "docstatus": 0,
  "doctype": "Translation",
  "language": "en",
  "modified": "2019-02-12 22:28:26.097960",
  "name": "9e1c915d54",
  "source_name": "Issue",
  "target_name": "Maintenance Job Card"
 },
 {
  "docstatus": 0,
  "doctype": "Translation",
  "language": "en",
  "modified": "2019-02-12 22:28:26.103694",
  "name": "eb9a7ae7cb",
  "source_name": "Issue",
  "target_name": "Maintenance Job Card"
 },
 {
  "docstatus": 0,
  "doctype": "Translation",
  "language": "en",
  "modified": "2019-02-12 22:28:26.109330",
  "name": "5549275846",
  "source_name": "Issue",
  "target_name": "Maintenance Job Card"
 },
 {
  "docstatus": 0,
  "doctype": "Translation",
  "language": "en",
  "modified": "2019-02-12 22:28:26.115234",
  "name": "5f1a84e9b0",
  "source_name": "Issue",
  "target_name": "Maintenance Job Card"
 },
 {
  "docstatus": 0,
  "doctype": "Translation",
  "language": "en",
  "modified": "2019-02-12 22:28:26.120992",
  "name": "ba962814aa",
  "source_name": "Issue",
  "target_name": "Maintenance Job Card"
 },
 {
  "docstatus": 0,
  "doctype": "Translation",
  "language": "en",
  "modified": "2019-02-12 22:28:26.126765",
  "name": "97aea5da68",
  "source_name": "Issue",
  "target_name": "Maintenance Job Card"
 },
 {
  "docstatus": 0,
  "doctype": "Translation",
  "language": "en",
  "modified": "2019-02-12 22:28:26.132540",
  "name": "85daa14cec",
  "source_name": "Issue",
  "target_name": "Maintenance Job Card"
 },
 {
  "docstatus": 0,
  "doctype": "Translation",
  "language": "en",
  "modified": "2019-02-12 22:28:26.138159",
  "name": "c5ff7566b2",
  "source_name": "Issue",
  "target_name": "Maintenance Job Card"
 },
 {
  "docstatus": 0,
  "doctype": "Translation",
  "language": "en",
  "modified": "2019-02-12 22:28:26.143738",
  "name": "b8997be573",
  "source_name": "Issue",
  "target_name": "Maintenance Job Card"
 },
 {
  "docstatus": 0,
  "doctype": "Translation",
  "language": "en",
  "modified": "2019-02-12 22:28:26.149524",
  "name": "5eb7ec88ae",
  "source_name": "Issue",
  "target_name": "Maintenance Job Card"
 },
 {
  "docstatus": 0,
  "doctype": "Translation",
  "language": "en",
  "modified": "2019-02-12 22:28:26.155180",
  "name": "5c875ccaca",
  "source_name": "Issue",
  "target_name": "Maintenance Job Card"
 },
 {
  "docstatus": 0,
  "doctype": "Translation",
  "language": "en",
  "modified": "2019-02-12 22:28:26.160884",
  "name": "2f3af6f23a",
  "source_name": "Issue",
  "target_name": "Maintenance Job Card"
 },
 {
  "docstatus": 0,
  "doctype": "Translation",
  "language": "en",
  "modified": "2019-02-12 22:28:26.166560",
  "name": "ea58fdf387",
  "source_name": "Issue",
  "target_name": "Maintenance Job Card"
 },
 {
  "docstatus": 0,
  "doctype": "Translation",
  "language": "en",
  "modified": "2019-02-12 22:28:26.172424",
  "name": "56b47e46e5",
  "source_name": "Issue",
  "target_name": "Maintenance Job Card"
 },
 {
  "docstatus": 0,
  "doctype": "Translation",
  "language": "en",
  "modified": "2019-02-12 22:28:26.178225",
  "name": "9371158b0a",
  "source_name": "Issue",
  "target_name": "Maintenance Job Card"
 },
 {
  "docstatus": 0,
  "doctype": "Translation",
  "language": "en",
  "modified": "2019-02-12 22:28:26.183945",
  "name": "893bba5b1a",
  "source_name": "Issue",
  "target_name": "Maintenance Job Card"
 },
 {
  "docstatus": 0,
  "doctype": "Translation",
  "language": "en",
  "modified": "2019-02-12 22:28:26.189811",
  "name": "3584a24bce",
  "source_name": "Issue",
  "target_name": "Maintenance Job Card"
 },
 {
  "docstatus": 0,
  "doctype": "Translation",
  "language": "en",
  "modified": "2019-02-12 22:28:26.195644",
  "name": "f063567855",
  "source_name": "Issue",
  "target_name": "Maintenance Job Card"
 },
 {
  "docstatus": 0,
  "doctype": "Translation",
  "language": "en",
  "modified": "2019-02-12 22:28:26.201330",
  "name": "4f5d5ceca0",
  "source_name": "Issue",
  "target_name": "Maintenance Job Card"
 },
 {
  "docstatus": 0,
  "doctype": "Translation",
  "language": "en",
  "modified": "2019-02-12 22:28:26.207011",
  "name": "320b3275b5",
  "source_name": "Issue",
  "target_name": "Maintenance Job Card"
 },
 {
  "docstatus": 0,
  "doctype": "Translation",
  "language": "en",
  "modified": "2019-02-12 22:28:26.212705",
  "name": "edbd391ed7",
  "source_name": "Issue",
  "target_name": "Maintenance Job Card"
 },
 {
  "docstatus": 0,
  "doctype": "Translation",
  "language": "en",
  "modified": "2019-02-12 22:28:26.218381",
  "name": "9772ed5e14",
  "source_name": "Issue",
  "target_name": "Maintenance Job Card"
 },
 {
  "docstatus": 0,
  "doctype": "Translation",
  "language": "en",
  "modified": "2019-02-12 22:28:26.224065",
  "name": "78b8ccdd6f",
  "source_name": "Issue",
  "target_name": "Maintenance Job Card"
 },
 {
  "docstatus": 0,
  "doctype": "Translation",
  "language": "en",
  "modified": "2019-02-12 22:28:26.229686",
  "name": "e2dd298bcb",
  "source_name": "Issue",
  "target_name": "Maintenance Job Card"
 },
 {
  "docstatus": 0,
  "doctype": "Translation",
  "language": "en",
  "modified": "2019-02-12 22:28:26.235344",
  "name": "e5bde51ce2",
  "source_name": "Issue",
  "target_name": "Maintenance Job Card"
 },
 {
  "docstatus": 0,
  "doctype": "Translation",
  "language": "en",
  "modified": "2019-02-12 22:28:26.240924",
  "name": "2f7f923f4c",
  "source_name": "Issue",
  "target_name": "Maintenance Job Card"
 },
 {
  "docstatus": 0,
  "doctype": "Translation",
  "language": "en",
  "modified": "2019-02-12 22:28:26.246609",
  "name": "fb41853d69",
  "source_name": "Issue",
  "target_name": "Maintenance Job Card"
 },
 {
  "docstatus": 0,
  "doctype": "Translation",
  "language": "en",
  "modified": "2019-02-12 22:28:26.252331",
  "name": "272ecc9b0a",
  "source_name": "Issue",
  "target_name": "Maintenance Job Card"
 },
 {
  "docstatus": 0,
  "doctype": "Translation",
  "language": "en",
  "modified": "2019-02-12 22:28:26.257958",
  "name": "a12b803ede",
  "source_name": "Issue",
  "target_name": "Maintenance Job Card"
 },
 {
  "docstatus": 0,
  "doctype": "Translation",
  "language": "en",
  "modified": "2019-02-12 22:28:26.263643",
  "name": "0a1a0a60c1",
  "source_name": "Issue",
  "target_name": "Maintenance Job Card"
 },
 {
  "docstatus": 0,
  "doctype": "Translation",
  "language": "en",
  "modified": "2019-02-12 22:28:26.269320",
  "name": "b054c7aeeb",
  "source_name": "Issue",
  "target_name": "Maintenance Job Card"
 },
 {
  "docstatus": 0,
  "doctype": "Translation",
  "language": "en",
  "modified": "2019-02-12 22:28:26.274969",
  "name": "92fa7874a3",
  "source_name": "Issue",
  "target_name": "Maintenance Job Card"
 },
 {
  "docstatus": 0,
  "doctype": "Translation",
  "language": "en",
  "modified": "2019-02-12 22:28:26.280625",
  "name": "a108b1eed4",
  "source_name": "Issue",
  "target_name": "Maintenance Job Card"
 },
 {
  "docstatus": 0,
  "doctype": "Translation",
  "language": "en",
  "modified": "2019-02-12 22:28:26.286261",
  "name": "a12d8c130c",
  "source_name": "Issue",
  "target_name": "Maintenance Job Card"
 },
 {
  "docstatus": 0,
  "doctype": "Translation",
  "language": "en",
  "modified": "2019-02-12 22:28:26.291927",
  "name": "cd8f5fc103",
  "source_name": "Issue",
  "target_name": "Maintenance Job Card"
 },
 {
  "docstatus": 0,
  "doctype": "Translation",
  "language": "en",
  "modified": "2019-02-12 22:28:26.297552",
  "name": "8a756c0073",
  "source_name": "Issue",
  "target_name": "Maintenance Job Card"
 },
 {
  "docstatus": 0,
  "doctype": "Translation",
  "language": "en",
  "modified": "2019-02-12 22:28:26.303353",
  "name": "62c7b1cdfd",
  "source_name": "Issue",
  "target_name": "Maintenance Job Card"
 },
 {
  "docstatus": 0,
  "doctype": "Translation",
  "language": "en",
  "modified": "2019-02-12 22:28:26.309075",
  "name": "d27e41c02f",
  "source_name": "Issue",
  "target_name": "Maintenance Job Card"
 },
 {
  "docstatus": 0,
  "doctype": "Translation",
  "language": "en",
  "modified": "2019-02-12 22:28:26.314999",
  "name": "013d1894d9",
  "source_name": "Issue",
  "target_name": "Maintenance Job Card"
 },
 {
  "docstatus": 0,
  "doctype": "Translation",
  "language": "en",
  "modified": "2019-02-12 22:28:26.320792",
  "name": "44d08de61f",
  "source_name": "Issue",
  "target_name": "Maintenance Job Card"
 },
 {
  "docstatus": 0,
  "doctype": "Translation",
  "language": "en",
  "modified": "2019-02-12 22:28:26.326444",
  "name": "fb9b4feb4f",
  "source_name": "Issue",
  "target_name": "Maintenance Job Card"
 },
 {
  "docstatus": 0,
  "doctype": "Translation",
  "language": "en",
  "modified": "2019-02-12 22:28:26.332290",
  "name": "fc539ab1f6",
  "source_name": "Issue",
  "target_name": "Maintenance Job Card"
 },
 {
  "docstatus": 0,
  "doctype": "Translation",
  "language": "en",
  "modified": "2019-02-12 22:28:26.337969",
  "name": "bf49e57543",
  "source_name": "Issue",
  "target_name": "Maintenance Job Card"
 },
 {
  "docstatus": 0,
  "doctype": "Translation",
  "language": "en",
  "modified": "2019-02-12 22:28:26.343618",
  "name": "a837c5c32d",
  "source_name": "Issue",
  "target_name": "Maintenance Job Card"
 },
 {
  "docstatus": 0,
  "doctype": "Translation",
  "language": "en",
  "modified": "2019-02-12 22:28:26.349413",
  "name": "c9c031a04d",
  "source_name": "Issue",
  "target_name": "Maintenance Job Card"
 },
 {
  "docstatus": 0,
  "doctype": "Translation",
  "language": "en",
  "modified": "2019-02-12 22:28:26.355324",
  "name": "36a0f0d059",
  "source_name": "Issue",
  "target_name": "Maintenance Job Card"
 },
 {
  "docstatus": 0,
  "doctype": "Translation",
  "language": "en",
  "modified": "2019-02-12 22:28:26.361314",
  "name": "9289b87b10",
  "source_name": "Issue",
  "target_name": "Maintenance Job Card"
 },
 {
  "docstatus": 0,
  "doctype": "Translation",
  "language": "en",
  "modified": "2019-02-12 22:28:26.367148",
  "name": "d234f404bb",
  "source_name": "Issue",
  "target_name": "Maintenance Job Card"
 },
 {
  "docstatus": 0,
  "doctype": "Translation",
  "language": "en",
  "modified": "2019-02-12 22:28:26.372971",
  "name": "c3228b4804",
  "source_name": "Issue",
  "target_name": "Maintenance Job Card"
 },
 {
  "docstatus": 0,
  "doctype": "Translation",
  "language": "en",
  "modified": "2019-02-12 22:28:26.378842",
  "name": "180d4368b6",
  "source_name": "Issue",
  "target_name": "Maintenance Job Card"
 },
 {
  "docstatus": 0,
  "doctype": "Translation",
  "language": "en",
  "modified": "2019-02-12 22:28:26.384714",
  "name": "94a65274c1",
  "source_name": "Issue",
  "target_name": "Maintenance Job Card"
 },
 {
  "docstatus": 0,
  "doctype": "Translation",
  "language": "en",
  "modified": "2019-02-12 22:28:26.390451",
  "name": "d32ad0130d",
  "source_name": "Issue",
  "target_name": "Maintenance Job Card"
 },
 {
  "docstatus": 0,
  "doctype": "Translation",
  "language": "en",
  "modified": "2019-02-12 22:28:26.396284",
  "name": "6a646ece03",
  "source_name": "Issue",
  "target_name": "Maintenance Job Card"
 },
 {
  "docstatus": 0,
  "doctype": "Translation",
  "language": "en",
  "modified": "2019-02-12 22:28:26.402060",
  "name": "ac4af07dad",
  "source_name": "Issue",
  "target_name": "Maintenance Job Card"
 },
 {
  "docstatus": 0,
  "doctype": "Translation",
  "language": "en",
  "modified": "2019-02-12 22:28:26.407883",
  "name": "396fd31575",
  "source_name": "Issue",
  "target_name": "Maintenance Job Card"
 },
 {
  "docstatus": 0,
  "doctype": "Translation",
  "language": "en",
  "modified": "2019-02-12 22:28:26.413827",
  "name": "93e07a1030",
  "source_name": "Issue",
  "target_name": "Maintenance Job Card"
 },
 {
  "docstatus": 0,
  "doctype": "Translation",
  "language": "en",
  "modified": "2019-02-12 22:28:26.419629",
  "name": "0a387a83a3",
  "source_name": "Issue",
  "target_name": "Maintenance Job Card"
 },
 {
  "docstatus": 0,
  "doctype": "Translation",
  "language": "en",
  "modified": "2019-02-12 22:28:26.425349",
  "name": "86085f94a3",
  "source_name": "Issue",
  "target_name": "Maintenance Job Card"
 },
 {
  "docstatus": 0,
  "doctype": "Translation",
  "language": "en",
  "modified": "2019-02-12 22:28:26.431085",
  "name": "c1bed8fb96",
  "source_name": "Issue",
  "target_name": "Maintenance Job Card"
 },
 {
  "docstatus": 0,
  "doctype": "Translation",
  "language": "en",
  "modified": "2019-02-12 22:28:26.436813",
  "name": "05578be9de",
  "source_name": "Issue",
  "target_name": "Maintenance Job Card"
 },
 {
  "docstatus": 0,
  "doctype": "Translation",
  "language": "en",
  "modified": "2019-02-12 22:28:26.442529",
  "name": "1c8877b902",
  "source_name": "Issue",
  "target_name": "Maintenance Job Card"
 },
 {
  "docstatus": 0,
  "doctype": "Translation",
  "language": "en",
  "modified": "2019-02-12 22:28:26.448230",
  "name": "5a9e6ff912",
  "source_name": "Issue",
  "target_name": "Maintenance Job Card"
 },
 {
  "docstatus": 0,
  "doctype": "Translation",
  "language": "en",
  "modified": "2019-02-12 22:28:26.453989",
  "name": "37010d3446",
  "source_name": "Issue",
  "target_name": "Maintenance Job Card"
 },
 {
  "docstatus": 0,
  "doctype": "Translation",
  "language": "en",
  "modified": "2019-02-12 22:28:26.460065",
  "name": "a92da2a09a",
  "source_name": "Issue",
  "target_name": "Maintenance Job Card"
 },
 {
  "docstatus": 0,
  "doctype": "Translation",
  "language": "en",
  "modified": "2019-02-12 22:28:26.465850",
  "name": "1fc4b5f05f",
  "source_name": "Issue",
  "target_name": "Maintenance Job Card"
 },
 {
  "docstatus": 0,
  "doctype": "Translation",
  "language": "en",
  "modified": "2019-02-12 22:28:26.471582",
  "name": "c1100437fe",
  "source_name": "Issue",
  "target_name": "Maintenance Job Card"
 },
 {
  "docstatus": 0,
  "doctype": "Translation",
  "language": "en",
  "modified": "2019-02-12 22:28:26.477402",
  "name": "df8cfa3d88",
  "source_name": "Issue",
  "target_name": "Maintenance Job Card"
 },
 {
  "docstatus": 0,
  "doctype": "Translation",
  "language": "en",
  "modified": "2019-02-12 22:28:26.483197",
  "name": "0d29ba3025",
  "source_name": "Issue",
  "target_name": "Maintenance Job Card"
 },
 {
  "docstatus": 0,
  "doctype": "Translation",
  "language": "en",
  "modified": "2019-02-12 22:28:26.488931",
  "name": "4f33ab2358",
  "source_name": "Issue",
  "target_name": "Maintenance Job Card"
 },
 {
  "docstatus": 0,
  "doctype": "Translation",
  "language": "en",
  "modified": "2019-02-12 22:28:26.494793",
  "name": "ea6c3e48d6",
  "source_name": "Issue",
  "target_name": "Maintenance Job Card"
 },
 {
  "docstatus": 0,
  "doctype": "Translation",
  "language": "en",
  "modified": "2019-02-12 22:28:26.500556",
  "name": "8a0213bb33",
  "source_name": "Issue",
  "target_name": "Maintenance Job Card"
 },
 {
  "docstatus": 0,
  "doctype": "Translation",
  "language": "en",
  "modified": "2019-02-12 22:28:26.506507",
  "name": "819148b4b1",
  "source_name": "Issue",
  "target_name": "Maintenance Job Card"
 },
 {
  "docstatus": 0,
  "doctype": "Translation",
  "language": "en",
  "modified": "2019-02-12 22:28:26.512758",
  "name": "8d097817af",
  "source_name": "Issue",
  "target_name": "Maintenance Job Card"
 },
 {
  "docstatus": 0,
  "doctype": "Translation",
  "language": "en",
  "modified": "2019-02-12 22:28:26.518517",
  "name": "50f47f993a",
  "source_name": "Issue",
  "target_name": "Maintenance Job Card"
 },
 {
  "docstatus": 0,
  "doctype": "Translation",
  "language": "en",
  "modified": "2019-02-12 22:28:26.524395",
  "name": "1c6cef3358",
  "source_name": "Issue",
  "target_name": "Maintenance Job Card"
 },
 {
  "docstatus": 0,
  "doctype": "Translation",
  "language": "en",
  "modified": "2019-02-12 22:28:26.530161",
  "name": "ec4078776c",
  "source_name": "Issue",
  "target_name": "Maintenance Job Card"
 },
 {
  "docstatus": 0,
  "doctype": "Translation",
  "language": "en",
  "modified": "2019-02-12 22:28:26.535988",
  "name": "8c07737573",
  "source_name": "Issue",
  "target_name": "Maintenance Job Card"
 },
 {
  "docstatus": 0,
  "doctype": "Translation",
  "language": "en",
  "modified": "2019-02-12 22:28:26.541648",
  "name": "3db98be713",
  "source_name": "Issue",
  "target_name": "Maintenance Job Card"
 },
 {
  "docstatus": 0,
  "doctype": "Translation",
  "language": "en",
  "modified": "2019-02-12 22:28:26.547358",
  "name": "5364d4be07",
  "source_name": "Issue",
  "target_name": "Maintenance Job Card"
 },
 {
  "docstatus": 0,
  "doctype": "Translation",
  "language": "en",
  "modified": "2019-02-12 22:28:26.553142",
  "name": "79ae3e09e4",
  "source_name": "Issue",
  "target_name": "Maintenance Job Card"
 },
 {
  "docstatus": 0,
  "doctype": "Translation",
  "language": "en",
  "modified": "2019-02-12 22:28:26.558993",
  "name": "5ed611825c",
  "source_name": "Issue",
  "target_name": "Maintenance Job Card"
 },
 {
  "docstatus": 0,
  "doctype": "Translation",
  "language": "en",
  "modified": "2019-02-12 22:28:26.564674",
  "name": "223199e6b8",
  "source_name": "Issue",
  "target_name": "Maintenance Job Card"
 },
 {
  "docstatus": 0,
  "doctype": "Translation",
  "language": "en",
  "modified": "2019-02-12 22:28:26.570344",
  "name": "d2ae9c8f34",
  "source_name": "Issue",
  "target_name": "Maintenance Job Card"
 },
 {
  "docstatus": 0,
  "doctype": "Translation",
  "language": "en",
  "modified": "2019-02-12 22:28:26.576036",
  "name": "e9689012d7",
  "source_name": "Issue",
  "target_name": "Maintenance Job Card"
 },
 {
  "docstatus": 0,
  "doctype": "Translation",
  "language": "en",
  "modified": "2019-02-12 22:28:26.581681",
  "name": "b1658d8183",
  "source_name": "Issue",
  "target_name": "Maintenance Job Card"
 },
 {
  "docstatus": 0,
  "doctype": "Translation",
  "language": "en",
  "modified": "2019-02-12 22:28:26.587498",
  "name": "a8dea777be",
  "source_name": "Issue",
  "target_name": "Maintenance Job Card"
 },
 {
  "docstatus": 0,
  "doctype": "Translation",
  "language": "en",
  "modified": "2019-02-12 22:28:26.593265",
  "name": "c657d44b77",
  "source_name": "Issue",
  "target_name": "Maintenance Job Card"
 },
 {
  "docstatus": 0,
  "doctype": "Translation",
  "language": "en",
  "modified": "2019-02-12 22:28:26.599063",
  "name": "792d21b57b",
  "source_name": "Issue",
  "target_name": "Maintenance Job Card"
 },
 {
  "docstatus": 0,
  "doctype": "Translation",
  "language": "en",
  "modified": "2019-02-12 22:28:26.604910",
  "name": "b9fd9bd5bd",
  "source_name": "Issue",
  "target_name": "Maintenance Job Card"
 },
 {
  "docstatus": 0,
  "doctype": "Translation",
  "language": "en",
  "modified": "2019-02-12 22:28:26.610712",
  "name": "d5084ec79b",
  "source_name": "Issue",
  "target_name": "Maintenance Job Card"
 },
 {
  "docstatus": 0,
  "doctype": "Translation",
  "language": "en",
  "modified": "2019-02-12 22:28:26.616523",
  "name": "38438d35e7",
  "source_name": "Issue",
  "target_name": "Maintenance Job Card"
 },
 {
  "docstatus": 0,
  "doctype": "Translation",
  "language": "en",
  "modified": "2019-02-12 22:28:26.622139",
  "name": "8f8d2b4f0a",
  "source_name": "Issue",
  "target_name": "Maintenance Job Card"
 },
 {
  "docstatus": 0,
  "doctype": "Translation",
  "language": "en",
  "modified": "2019-02-12 22:28:26.627732",
  "name": "67e44d828d",
  "source_name": "Issue",
  "target_name": "Maintenance Job Card"
 },
 {
  "docstatus": 0,
  "doctype": "Translation",
  "language": "en",
  "modified": "2019-02-12 22:28:26.633378",
  "name": "c70c5c03d2",
  "source_name": "Issue",
  "target_name": "Maintenance Job Card"
 },
 {
  "docstatus": 0,
  "doctype": "Translation",
  "language": "en",
  "modified": "2019-02-12 22:28:26.639182",
  "name": "7d417a4d54",
  "source_name": "Issue",
  "target_name": "Maintenance Job Card"
 },
 {
  "docstatus": 0,
  "doctype": "Translation",
  "language": "en",
  "modified": "2019-02-12 22:28:26.644914",
  "name": "0c34e0179e",
  "source_name": "Issue",
  "target_name": "Maintenance Job Card"
 },
 {
  "docstatus": 0,
  "doctype": "Translation",
  "language": "en",
  "modified": "2019-02-12 22:28:26.650701",
  "name": "8c777ec9ae",
  "source_name": "Issue",
  "target_name": "Maintenance Job Card"
 },
 {
  "docstatus": 0,
  "doctype": "Translation",
  "language": "en",
  "modified": "2019-02-12 22:28:26.656408",
  "name": "00fafa3fcb",
  "source_name": "Issue",
  "target_name": "Maintenance Job Card"
 },
 {
  "docstatus": 0,
  "doctype": "Translation",
  "language": "en",
  "modified": "2019-02-12 22:28:26.662113",
  "name": "856b6bacf0",
  "source_name": "Issue",
  "target_name": "Maintenance Job Card"
 },
 {
  "docstatus": 0,
  "doctype": "Translation",
  "language": "en",
  "modified": "2019-02-12 22:28:26.667852",
  "name": "4c251c530a",
  "source_name": "Issue",
  "target_name": "Maintenance Job Card"
 },
 {
  "docstatus": 0,
  "doctype": "Translation",
  "language": "en",
  "modified": "2019-02-12 22:28:26.673564",
  "name": "8a33c61499",
  "source_name": "Issue",
  "target_name": "Maintenance Job Card"
 }
]