{
 "custom_fields": [], 
 "custom_perms": [], 
 "doctype": "Contact", 
 "property_setters": [
  {
   "_assign": null, 
   "_comments": null, 
   "_liked_by": null, 
   "_user_tags": null, 
   "creation": "2018-12-27 19:31:42.315595", 
   "default_value": null, 
   "doc_type": "Contact", 
   "docstatus": 0, 
   "doctype_or_field": "DocField", 
   "field_name": "department", 
   "idx": 0, 
   "modified": "2018-12-27 19:31:42.315595", 
   "modified_by": "Administrator", 
   "name": "Contact-department-options", 
   "owner": "Administrator", 
   "parent": null, 
   "parentfield": null, 
   "parenttype": null, 
   "property": "options", 
   "property_type": "Text", 
   "value": "\nOutsourcing - Cleaning"
  }, 
  {
   "_assign": null, 
   "_comments": null, 
   "_liked_by": null, 
   "_user_tags": null, 
   "creation": "2018-12-27 19:31:42.312100", 
   "default_value": null, 
   "doc_type": "Contact", 
   "docstatus": 0, 
   "doctype_or_field": "DocField", 
   "field_name": "department", 
   "idx": 0, 
   "modified": "2018-12-27 19:31:42.312100", 
   "modified_by": "Administrator", 
   "name": "Contact-department-fieldtype", 
   "owner": "Administrator", 
   "parent": null, 
   "parentfield": null, 
   "parenttype": null, 
   "property": "fieldtype", 
   "property_type": "Select", 
   "value": "Select"
  }, 
  {
   "_assign": null, 
   "_comments": null, 
   "_liked_by": null, 
   "_user_tags": null, 
   "creation": "2018-12-27 19:31:42.291265", 
   "default_value": null, 
   "doc_type": "Contact", 
   "docstatus": 0, 
   "doctype_or_field": "DocType", 
   "field_name": null, 
   "idx": 0, 
   "modified": "2018-12-27 19:31:42.291265", 
   "modified_by": "Administrator", 
   "name": "Contact-read_only_onload", 
   "owner": "Administrator", 
   "parent": null, 
   "parentfield": null, 
   "parenttype": null, 
   "property": "read_only_onload", 
   "property_type": "Check", 
   "value": null
  }
 ], 
 "sync_on_migrate": 1
}